README.md
setup.py
cq/__init__.py
cq/aggregates.py
cq/app.py
cq/compat.py
cq/events.py
cq/exceptions.py
cq/genuuid.py
cq/handlers.py
cq/schemas.py
cq/settings.py
cq/storages.py
cq.egg-info/PKG-INFO
cq.egg-info/SOURCES.txt
cq.egg-info/dependency_links.txt
cq.egg-info/not-zip-safe
cq.egg-info/requires.txt
cq.egg-info/top_level.txt
cq/contrib/__init__.py
cq/contrib/django/__init__.py
cq/contrib/django/apps.py
cq/contrib/django/models.py
cq/contrib/django/shortcuts.py
cq/contrib/django/storages.py
cq/contrib/django/migrations/0001_initial.py
cq/contrib/django/migrations/0002_ts_field_index.py
cq/contrib/django/migrations/0003_event_aggregate_type.py
cq/contrib/django/migrations/0004_event_revision.py
cq/contrib/django/migrations/__init__.py
cq/contrib/sqlalchemy/__init__.py
cq/contrib/sqlalchemy/storage.py
cq/tests/__init__.py
cq/tests/app.py
cq/tests/test_aggregates.py
cq/tests/test_apps.py
cq/tests/test_entities.py
cq/tests/test_handlers.py
cq/tests/test_replay.py
cq/tests/test_repository.py
cq/tests/test_schemas.py
cq/tests/test_storages.py
cq/tests/test_upcasting.py