Metadata-Version: 1.0
Name: cq
Version: 0.13
Summary: simple cqrs implementation
Home-page: https://github.com/lukaszb/cq
Author: Lukasz Balcerzak
Author-email: lukaszbalcerzak@gmail.com
License: MIT
Platform: UNKNOWN
